{"page_meta":{"limit":50,"offset":650,"total":1410},"results":[{"location":{"lat":"51.47310","lon":"-0.38570"},"name":"Hounslow Wst Stn Loc"},{"location":{"lat":"50.83335","lon":"-0.18404"},"name":"Hove Portland Rd Loc"},{"location":{"lat":"50.82590","lon":"-0.16120"},"name":"Hove Western Rd Loc"},{"location":{"lat":"53.39280","lon":"-3.17748"},"name":"Hoylake Loc"},{"location":{"lat":"53.97879","lon":"-1.53423"},"name":"Hrgt Leeds Rd Loc"},{"location":{"lat":"51.18451","lon":"-0.16422"},"name":"Hrly Bonhurst Rd Loc"},{"location":{"lat":"51.58599","lon":"-0.09226"},"name":"Hrngy Wst Grn Rd Loc"},{"location":{"lat":"53.25037","lon":"-2.53818"},"name":"Hrtfd Chester Rd Loc"},{"location":{"lat":"51.49223","lon":"-0.20725"},"name":"Hsmith Nth End C Loc"},{"location":{"lat":"53.64593","lon":"-1.78509"},"name":"Huddersfield"},{"location":{"lat":"53.02641","lon":"-1.21954"},"name":"Huknl Watnall Rd Loc"},{"location":{"lat":"53.72327","lon":"-0.42005"},"name":"Hull"},{"location":{"lat":"53.74455","lon":"-0.34219"},"name":"Hull Jameson Str Loc"},{"location":{"lat":"52.93885","lon":"0.49184"},"name":"Hunstanton"},{"location":{"lat":"52.33150","lon":"-0.18176"},"name":"Huntingdon"},{"location":{"lat":"53.81252","lon":"-1.56901"},"name":"Hyde Park Loc"},{"location":{"lat":"51.07192","lon":"1.07644"},"name":"Hythe"},{"location":{"lat":"51.55656","lon":"0.06985"},"name":"Ilford"},{"location":{"lat":"53.61254","lon":"-0.22224"},"name":"Immingham Loc"},{"location":{"lat":"53.77514","lon":"-0.30335"},"name":"Ings Rd Loc"},{"location":{"lat":"53.52714","lon":"-1.10533"},"name":"Intake Loc"},{"location":{"lat":"55.91052","lon":"-4.86419"},"name":"Inverkip Loc"},{"location":{"lat":"52.06167","lon":"1.18218"},"name":"Ipsh Woodbrge Rd Loc"},{"location":{"lat":"52.05627","lon":"1.15572"},"name":"Ipswich"},{"location":{"lat":"55.60587","lon":"-4.66797"},"name":"Irvine"},{"location":{"lat":"50.70160","lon":"-1.30009"},"name":"Isle of Wight"},{"location":{"lat":"51.47495","lon":"-0.33841"},"name":"Islewrth Lndn Rd Loc"},{"location":{"lat":"51.56012","lon":"-0.12341"},"name":"Islgn Mercers Rd Loc"},{"location":{"lat":"51.52795","lon":"-0.10512"},"name":"Islgn St Jhns St Loc"},{"location":{"lat":"51.53420","lon":"-0.10773"},"name":"Islington"},{"location":{"lat":"51.53105","lon":"-0.12054"},"name":"Isltn Pntnvle Rd Loc"},{"location":{"lat":"51.54605","lon":"-0.10111"},"name":"Istn St Pauls Rd Loc"},{"location":{"lat":"51.51616","lon":"-0.20493"},"name":"KC Portobello Rd Loc"},{"location":{"lat":"52.93182","lon":"-1.49030"},"name":"Kedleston Rd Loc"},{"location":{"lat":"53.86886","lon":"-1.90465"},"name":"Keighley"},{"location":{"lat":"55.59022","lon":"-2.42681"},"name":"Kelso"},{"location":{"lat":"51.23553","lon":"-1.13920"},"name":"Kempshott"},{"location":{"lat":"52.11740","lon":"-0.49603"},"name":"Kempston"},{"location":{"lat":"54.34087","lon":"-2.74003"},"name":"Kendal"},{"location":{"lat":"52.34060","lon":"-1.57789"},"name":"Kenilworth"},{"location":{"lat":"51.55029","lon":"-0.14115"},"name":"Kentish Town Loc"},{"location":{"lat":"51.58147","lon":"-0.31517"},"name":"Kenton"},{"location":{"lat":"52.40288","lon":"-0.72711"},"name":"Kettering"},{"location":{"lat":"51.41438","lon":"-2.49714"},"name":"Keynsham Mrkt Pl Loc"},{"location":{"lat":"52.87668","lon":"-1.08893"},"name":"Keyworth Loc"},{"location":{"lat":"51.40238","lon":"-0.30430"},"name":"Kgstn Penrhyn Rd Loc"},{"location":{"lat":"51.46178","lon":"0.02761"},"name":"Kidbrooke Village LC"},{"location":{"lat":"52.39137","lon":"-2.25407"},"name":"Kidderminster"},{"location":{"lat":"51.80890","lon":"-1.27765"},"name":"Kidlington"},{"location":{"lat":"51.53865","lon":"-0.19403"},"name":"Kilburn"}]}
